grpfpy/__init__.py
grpfpy/_grpfpy.cpython-39-x86_64-linux-gnu.so
grpfpy/core.py
grpfpy/version.py
grpfpy-0.1.22.dist-info/METADATA
grpfpy-0.1.22.dist-info/WHEEL
grpfpy-0.1.22.dist-info/top_level.txt
grpfpy-0.1.22.dist-info/RECORD
grpfpy-0.1.22.dist-info/licenses/LICENSE
