Metadata-Version: 2.4
Name: grpfpy
Version: 0.1.22
Summary: the Global complex Root and Pole Finding (GRPF) algorithm.
Home-page: https://github.com/allegro0132/grpfc
Author: Ziang Wang
Platform: any
License-File: LICENSE
Requires-Dist: numpy
Provides-Extra: test
Requires-Dist: pytest; extra == "test"
Dynamic: author
Dynamic: description
Dynamic: description-content-type
Dynamic: home-page
Dynamic: license-file
Dynamic: platform
Dynamic: provides-extra
Dynamic: requires-dist
Dynamic: summary
